PyMn/__init__.py
PyMn/bot.py
PyMn/exceptions.py
PyMn/group_manager.py
PyMn/keyboards.py
PyMn/security_manager.py
PyMn/telegram_extended.py
PyMn/telegram_pro.py
PyMn/types.py
PyMn/userbot.py
PyMn/utils.py
pymn-1.1.0.dist-info/LICENSE
pymn-1.1.0.dist-info/METADATA
pymn-1.1.0.dist-info/WHEEL
pymn-1.1.0.dist-info/top_level.txt
pymn-1.1.0.dist-info/RECORD
