Metadata-Version: 2.1
Name: pymn
Version: 1.1.0
Summary: کتابخانه قدرتمند برای ساخت ربات‌های تلگرام با امکانات پیشرفته
Home-page: https://github.com/DevMoEiN/PyMn
Author: DevMoEiN
Author-email: DevMoEiN <your-email@example.com>
License: MIT License
Project-URL: Homepage, https://github.com/DevMoEiN/PyMn
Project-URL: Documentation, https://github.com/DevMoEiN/PyMn/wiki
Project-URL: Repository, https://github.com/DevMoEiN/PyMn.git
Project-URL: Bug Tracker, https://github.com/DevMoEiN/PyMn/issues
Keywords: telegram,bot,api,python,library,persian
Classifier: Development Status :: 5 - Production/Stable
Classifier: Intended Audience :: Developers
Classifier: License :: OSI Approved :: MIT License
Classifier: Operating System :: OS Independent
Classifier: Programming Language :: Python :: 3
Classifier: Programming Language :: Python :: 3.7
Classifier: Programming Language :: Python :: 3.8
Classifier: Programming Language :: Python :: 3.9
Classifier: Programming Language :: Python :: 3.10
Classifier: Programming Language :: Python :: 3.11
Classifier: Topic :: Software Development :: Libraries :: Python Modules
Classifier: Topic :: Communications :: Chat
Classifier: Topic :: Internet
Requires-Python: >=3.8
License-File: LICENSE
Requires-Dist: requests>=2.25.1
Requires-Dist: aiohttp>=3.7.4
Requires-Dist: json5>=0.9.6
